sonusai_asr_cloud/__init__.py
sonusai_asr_cloud/asr_functions/__init__.py
sonusai_asr_cloud/asr_functions/aixplain_whisper.py
sonusai_asr_cloud/asr_functions/deepgram.py
sonusai_asr_cloud/asr_functions/google.py
sonusai_asr_cloud-0.2.0.dist-info/METADATA
sonusai_asr_cloud-0.2.0.dist-info/WHEEL
sonusai_asr_cloud-0.2.0.dist-info/RECORD
